sense2vec/__init__.py
sense2vec/component.py
sense2vec/prodigy_recipes.py
sense2vec/sense2vec.py
sense2vec/util.py
sense2vec/tests/__init__.py
sense2vec/tests/test_component.py
sense2vec/tests/test_issue155.py
sense2vec/tests/test_model.py
sense2vec/tests/test_sense2vec.py
sense2vec/tests/test_util.py
sense2vec/tests/data/cache
sense2vec/tests/data/cfg
sense2vec/tests/data/freqs.json
sense2vec/tests/data/key2row
sense2vec/tests/data/strings.json
sense2vec/tests/data/vectors
sense2vec-2.0.2.dist-info/LICENSE
sense2vec-2.0.2.dist-info/METADATA
sense2vec-2.0.2.dist-info/WHEEL
sense2vec-2.0.2.dist-info/entry_points.txt
sense2vec-2.0.2.dist-info/top_level.txt
sense2vec-2.0.2.dist-info/zip-safe
sense2vec-2.0.2.dist-info/RECORD
