Metadata-Version: 2.1
Name: sense2vec
Version: 2.0.2
Summary: Contextually-keyed word vectors
Home-page: https://github.com/explosion/sense2vec
Author: Explosion
Author-email: contact@explosion.ai
License: MIT
Classifier: Development Status :: 5 - Production/Stable
Classifier: Environment :: Console
Classifier: Intended Audience :: Developers
Classifier: Intended Audience :: Science/Research
Classifier: License :: OSI Approved :: MIT License
Classifier: Operating System :: POSIX :: Linux
Classifier: Operating System :: MacOS :: MacOS X
Classifier: Operating System :: Microsoft :: Windows
Classifier: Programming Language :: Python :: 3
Classifier: Programming Language :: Python :: 3.6
Classifier: Programming Language :: Python :: 3.7
Classifier: Programming Language :: Python :: 3.8
Classifier: Programming Language :: Python :: 3.9
Classifier: Programming Language :: Python :: 3.10
Classifier: Programming Language :: Python :: 3.11
Classifier: Topic :: Scientific/Engineering
Requires-Python: >=3.6
License-File: LICENSE
Requires-Dist: spacy (<4.0.0,>=3.0.0)
Requires-Dist: wasabi (<1.2.0,>=0.8.1)
Requires-Dist: srsly (<3.0.0,>=2.4.0)
Requires-Dist: catalogue (<2.1.0,>=2.0.1)
Requires-Dist: numpy (>=1.15.0)
Requires-Dist: importlib-metadata (>=0.20) ; python_version < "3.8"
